MANIFEST.in
README.txt
setup.cfg
setup.py
Sweepy.egg-info/PKG-INFO
Sweepy.egg-info/SOURCES.txt
Sweepy.egg-info/dependency_links.txt
Sweepy.egg-info/entry_points.txt
Sweepy.egg-info/not-zip-safe
Sweepy.egg-info/paster_plugins.txt
Sweepy.egg-info/requires.txt
Sweepy.egg-info/top_level.txt
sweepy/__init__.py
sweepy/websetup.py
sweepy/config/__init__.py
sweepy/config/deployment.ini_tmpl
sweepy/config/environment.py
sweepy/config/middleware.py
sweepy/config/routing.py
sweepy/controllers/__init__.py
sweepy/controllers/error.py
sweepy/controllers/game.py
sweepy/lib/__init__.py
sweepy/lib/app_globals.py
sweepy/lib/base.py
sweepy/lib/helpers.py
sweepy/model/__init__.py
sweepy/model/sweepy_engine.py
sweepy/public/index.html
sweepy/templates/grid.html
sweepy/tests/__init__.py
sweepy/tests/test_models.py
sweepy/tests/functional/__init__.py
sweepy/tests/functional/test_game.py