Metadata-Version: 1.0
Name: Sweepy
Version: 0.1.0
Summary: A very basic minesweeper clone written in Pylons
Home-page: http://www.memorista.com
Author: Francis O Reilly
Author-email: fran@memorista.com
License: GNU General Public License (GPL) 3.0 or any later version
Keywords: pylons sweepy minesweeper puzzle game demo
Platform: UNKNOWN
Classifier: Development Status :: 3 - Alpha
Classifier: Environment :: Web Environment
Classifier: License :: OSI Approved :: GNU General Public License (GPL)
Classifier: Framework :: Pylons
Classifier: Programming Language :: Python
Classifier: Topic :: Games/Entertainment :: Puzzle Games
